setup.py
hbasepy/__init__.py
hbasepy.egg-info/PKG-INFO
hbasepy.egg-info/SOURCES.txt
hbasepy.egg-info/dependency_links.txt
hbasepy.egg-info/not-zip-safe
hbasepy.egg-info/pbr.json
hbasepy.egg-info/requires.txt
hbasepy.egg-info/top_level.txt