Metadata-Version: 1.0
Name: hbasepy
Version: 0.1.1
Summary: Hbase REST client
Home-page: https://github.com/pasdoy/hbasepy
Author: pasdoy
Author-email: pasdoy12@gmail.com
License: MIT
Platform: UNKNOWN
